clonecat/__init__.py
clonecat/attributes.py
clonecat/clonecat.py
clonecat/import_helper.py
clonecat/registry.py
clonecat/types.py
clonecat/utils.py
clonecat/inspectors/__init__.py
clonecat/inspectors/base.py
clonecat/inspectors/dataclass.py
clonecat/inspectors/empty.py
clonecat/inspectors/model.py
clonecat-0.1.15.dist-info/METADATA
clonecat-0.1.15.dist-info/WHEEL
clonecat-0.1.15.dist-info/licenses/LICENSE
clonecat-0.1.15.dist-info/RECORD
