Metadata-Version: 2.4
Name: clonecat
Version: 0.1.15
Summary: CloneCat is a Python framework that helps you create perfect clones of your objects along with all their relationships.
Project-URL: Homepage, https://github.com/FlyingBird95/clonecat
Project-URL: Documentation, https://github.com/FlyingBird95/clonecat#readme
Project-URL: Repository, https://github.com/FlyingBird95/clonecat.git
Project-URL: Bug Tracker, https://github.com/FlyingBird95/clonecat/issues
Author: Patrick
License-File: LICENSE
Keywords: clone,copy,dataclasses,deepcopy,django,instances,pydantic,relations,sqlalchemy
Classifier: Development Status :: 4 - Beta
Classifier: Intended Audience :: Developers
Classifier: License :: OSI Approved :: MIT License
Classifier: Programming Language :: Python :: 3
Classifier: Programming Language :: Python :: 3.9
Classifier: Programming Language :: Python :: 3.10
Classifier: Programming Language :: Python :: 3.11
Classifier: Programming Language :: Python :: 3.12
Classifier: Programming Language :: Python :: 3.13
Classifier: Topic :: Software Development :: Libraries :: Python Modules
Classifier: Topic :: Utilities
Requires-Python: >=3.9
Provides-Extra: dev
Requires-Dist: bandit>=1.7; extra == 'dev'
Requires-Dist: black>=22.0; extra == 'dev'
Requires-Dist: bump2version>=1.0; extra == 'dev'
Requires-Dist: flake8>=5.0; extra == 'dev'
Requires-Dist: isort>=5.0; extra == 'dev'
Requires-Dist: mypy>=1.0; extra == 'dev'
Requires-Dist: pre-commit>=3.0; extra == 'dev'
Requires-Dist: pytest-cov>=4.0; extra == 'dev'
Requires-Dist: pytest>=7.0; extra == 'dev'
Requires-Dist: pytest>=8.3.5; extra == 'dev'
Requires-Dist: safety>=2.0; extra == 'dev'
Requires-Dist: sqlalchemy>=2.0.41; extra == 'dev'
